mcsi/__init__.py
mcsi/mcsi.cp313-win_amd64.pyd
mcsi/mcsi.cpp
mcsi-2025.0.1.dist-info/licenses/LICENSE
mcsi-2025.0.1.dist-info/METADATA
mcsi-2025.0.1.dist-info/WHEEL
mcsi-2025.0.1.dist-info/top_level.txt
mcsi-2025.0.1.dist-info/RECORD
