Metadata-Version: 2.4
Name: mcsi
Version: 2025.0.1
Summary: Calculates skewness of a distribution based on the mean, Mean-Centered Skewness Index (MCSI)
Author-email: Charles James <charlespencerjames@gmail.com>
License: MIT License
License-File: LICENSE
Requires-Dist: torch>=1.8.0
Dynamic: license-file
